tilly/__init__.py
tilly/cli.py
tilly/main.py
tilly/plugin.py
tilly/utils.py
tilly/commands/__init__.py
tilly/commands/hello.py
tilly/plugins/__init__.py
tilly/plugins/redirects.py
tilly/plugins/template_vars.py
tilly/search/__init__.py
tilly/search/pagefind.py
tilly/static/github-light.css
tilly/templates/404.html
tilly/templates/error.html
tilly/templates/google_analytics.html
tilly/templates/index.html
tilly/templates/snippet_display.html
tilly/templates/til_base.html
tilly/templates/pages/all.html
tilly/templates/pages/{topic}.html
tilly/templates/pages/tils/search.html
tilly/templates/pages/{topic}/{slug}.html
tilly-0.0.10.dist-info/LICENSE
tilly-0.0.10.dist-info/METADATA
tilly-0.0.10.dist-info/WHEEL
tilly-0.0.10.dist-info/entry_points.txt
tilly-0.0.10.dist-info/top_level.txt
tilly-0.0.10.dist-info/RECORD
