Metadata-Version: 2.1
Name: tilly
Version: 0.0.10
Summary: A cli for tracking Things I Learned (TIL)
Home-page: https://github.com/tilly-pub/tilly
Author: Ronald Luitwieler
Author-email: ronald.luitwieler@gmail.com
Classifier: Programming Language :: Python :: 3
Classifier: License :: OSI Approved :: MIT License
Classifier: Operating System :: OS Independent
Requires-Python: >=3.9
License-File: LICENSE
Requires-Dist: click>=8.0
Requires-Dist: pluggy>=1.0
Requires-Dist: setuptools
Requires-Dist: GitPython
Requires-Dist: sqlite-utils>=3.2
Requires-Dist: beautifulsoup4
Requires-Dist: httpx
Requires-Dist: datasette>=0.65.1
Requires-Dist: datasette-template-sql>=1.0.2
Requires-Dist: PyYAML>=6.0
Requires-Dist: pagefind
Requires-Dist: pagefind[bin]
